yamlmagic.py
yamlmagic-0.2.0.dist-info/WHEEL
yamlmagic-0.2.0.dist-info/DESCRIPTION.rst
yamlmagic-0.2.0.dist-info/metadata.json
yamlmagic-0.2.0.dist-info/RECORD
yamlmagic-0.2.0.dist-info/METADATA
yamlmagic-0.2.0.dist-info/top_level.txt
