Metadata-Version: 2.0
Name: yamlmagic
Version: 0.2.0
Summary: a YAML magic for IPython notebooks
Home-page: http://github.com/bollwyvl/yamlmagic
Author: Nicholas Bollweg
Author-email: nick.bollweg@gmail.com
License: BSD
Keywords: IPython yaml
Platform: UNKNOWN
Classifier: Topic :: Utilities
Classifier: Framework :: IPython
Classifier: Natural Language :: English
Classifier: Programming Language :: Python
Classifier: Intended Audience :: Developers
Classifier: Development Status :: 3 - Alpha
Classifier: Operating System :: OS Independent
Classifier: Programming Language :: Python :: 3
Classifier: License :: OSI Approved :: BSD License
Classifier: Topic :: Software Development :: Testing
